<?xml version="1.0" encoding="UTF-8"?>
<STEP-ProductInformation ContextID="Context1" WorkspaceID="Approved" UseContextLocale="false">
    <Qualifiers>
        <Qualifier ID="en-US">
            <DimensionPointLink DimensionPointID="en-US"></DimensionPointLink>
        </Qualifier>
    </Qualifiers>
    <ListsOfValues>
        <ListOfValue ID="DeactivatedLOV" ParentID="MetaDataLOVs" AllowUserValueAddition="false" UseValueID="true">
            <Name QualifierID="en-US">Deactivated LOV</Name>
            <Validation BaseType="text" MinValue="" MaxValue="" MaxLength="100" InputMask=""></Validation>
            <Value ID="false">No</Value>
            <Value ID="true">Yes</Value>
        </ListOfValue>
    </ListsOfValues>
</STEP-ProductInformation>